win_mcp_server/__init__.py
win_mcp_server/credentials.py
win_mcp_server/server.py
win_mcp_server-0.2.3.dist-info/LICENSE
win_mcp_server-0.2.3.dist-info/METADATA
win_mcp_server-0.2.3.dist-info/WHEEL
win_mcp_server-0.2.3.dist-info/entry_points.txt
win_mcp_server-0.2.3.dist-info/top_level.txt
win_mcp_server-0.2.3.dist-info/RECORD
