Metadata-Version: 2.1
Name: win-mcp-server
Version: 0.2.3
Summary: MCP server for Windows Remote Management (WinRM) with secure domain authentication
Author-email: Rory McMahon <rory.mcmahon@vocus.com.au>
License: MIT
Project-URL: Homepage, https://github.com/rorymcmahon/win-mcp-server
Project-URL: Repository, https://github.com/rorymcmahon/win-mcp-server
Project-URL: Issues, https://github.com/rorymcmahon/win-mcp-server/issues
Project-URL: Documentation, https://github.com/rorymcmahon/win-mcp-server#readme
Keywords: mcp,winrm,windows,remote,management,powershell
Classifier: Development Status :: 4 - Beta
Classifier: Intended Audience :: Developers
Classifier: License :: OSI Approved :: MIT License
Classifier: Operating System :: OS Independent
Classifier: Programming Language :: Python :: 3
Classifier: Programming Language :: Python :: 3.8
Classifier: Programming Language :: Python :: 3.9
Classifier: Programming Language :: Python :: 3.10
Classifier: Programming Language :: Python :: 3.11
Classifier: Programming Language :: Python :: 3.12
Classifier: Topic :: Software Development :: Libraries :: Python Modules
Classifier: Topic :: System :: Systems Administration
Classifier: Topic :: System :: Networking
Requires-Python: >=3.8
License-File: LICENSE
Requires-Dist: mcp==1.14.1
Requires-Dist: pywinrm==0.4.3
Provides-Extra: dev
Requires-Dist: pytest==8.3.3; extra == "dev"
Requires-Dist: pytest-asyncio==0.24.0; extra == "dev"
Requires-Dist: black==24.8.0; extra == "dev"
Requires-Dist: isort==5.13.2; extra == "dev"
Provides-Extra: security
Requires-Dist: safety>=3.0.0; extra == "security"
Requires-Dist: pip-audit>=2.6.0; extra == "security"
